dasst/__init__.py
dasst/constants.py
dasst/py.typed
dasst/simulation.py
dasst/time_utils.py
dasst/types.py
dasst/version.py
dasst/distributions/__init__.py
dasst/distributions/kernel_density_estimation.py
dasst/ejection_models/__init__.py
dasst/ejection_models/comets/__init__.py
dasst/ejection_models/comets/sublimation.py
dasst/orbit_determination/__init__.py
dasst/orbit_determination/methods.py
dasst/plot/__init__.py
dasst/plot/colors.py
dasst/propagators/__init__.py
dasst/propagators/rebound_compiler.py
dasst/propagators/rebound_interface.py
dasst/sampling/__init__.py
dasst/similarity/__init__.py
dasst/similarity/ca_criteria.py
dasst/similarity/d_criteria.py
pydasst-0.1.0.dist-info/licenses/LICENSE
pydasst-0.1.0.dist-info/METADATA
pydasst-0.1.0.dist-info/WHEEL
pydasst-0.1.0.dist-info/top_level.txt
pydasst-0.1.0.dist-info/RECORD
