Metadata-Version: 2.4
Name: pydasst
Version: 0.1.0
Summary: Dynamical Astronomy Statistical Simulations Toolbox in Python
Author-email: Daniel Kastinen <daniel.kastinen@irf.se>
Maintainer-email: Daniel Kastinen <daniel.kastinen@irf.se>
License:                     GNU GENERAL PUBLIC LICENSE
Project-URL: Documentation, https://danielk.developer.irf.se/dasst/
Project-URL: Repository, https://github.com/danielk333/dasst
Classifier: Intended Audience :: Science/Research
Classifier: Programming Language :: Python :: 3
Classifier: Topic :: Scientific/Engineering :: Physics
Classifier: Operating System :: OS Independent
Requires-Python: >=3.9
License-File: LICENSE
Requires-Dist: tqdm>=4.32.1
Requires-Dist: scipy>=1.3.0
Requires-Dist: numpy>=1.16.4
Requires-Dist: matplotlib>=3.1.0
Requires-Dist: pandas>=2.0.3
Requires-Dist: pyorb>=0.5.4
Requires-Dist: astropy>=5.3.1
Requires-Dist: jplephem>=2.23
Requires-Dist: rebound>=4.4.2
Requires-Dist: reboundx>=4.2.2
Requires-Dist: spacecoords>=0.1.3
Provides-Extra: develop
Requires-Dist: pytest; extra == "develop"
Requires-Dist: flake8; extra == "develop"
Requires-Dist: wheel; extra == "develop"
Requires-Dist: build; extra == "develop"
Requires-Dist: twine; extra == "develop"
Requires-Dist: pytest-cov; extra == "develop"
Requires-Dist: matplotlib; extra == "develop"
Requires-Dist: ipykernel; extra == "develop"
Requires-Dist: radon; extra == "develop"
Requires-Dist: numpydoc; extra == "develop"
Requires-Dist: pre-commit; extra == "develop"
Requires-Dist: black; extra == "develop"
Requires-Dist: auditwheel; extra == "develop"
Requires-Dist: patchelf; extra == "develop"
Requires-Dist: mkdocs-material; extra == "develop"
Requires-Dist: mkdocstrings[python]; extra == "develop"
Requires-Dist: mkdocs-jupyter; extra == "develop"
Requires-Dist: mkdocs-gen-files; extra == "develop"
Requires-Dist: mkdocs-literate-nav; extra == "develop"
Requires-Dist: mkdocs-section-index; extra == "develop"
Dynamic: license-file
